Metadata-Version: 2.1
Name: ER3
Version: 0.0.1
Summary: For the poweruser.
Home-page: UNKNOWN
Author: Parent: MS9
Author-email: <pycodermaximos@gmail.com>
License: UNKNOWN
Keywords: python,math,cmath,eazy,easy,better
Platform: UNKNOWN
Classifier: Development Status :: 1 - Planning
Classifier: Intended Audience :: Developers
Classifier: Programming Language :: Python :: 3
Classifier: Operating System :: Unix
Classifier: Operating System :: MacOS :: MacOS X
Classifier: Operating System :: Microsoft :: Windows
